CHANGES.txt
README.txt
setup.py
Products/__init__.py
Products.BooleanIndex.egg-info/PKG-INFO
Products.BooleanIndex.egg-info/SOURCES.txt
Products.BooleanIndex.egg-info/dependency_links.txt
Products.BooleanIndex.egg-info/namespace_packages.txt
Products.BooleanIndex.egg-info/not-zip-safe
Products.BooleanIndex.egg-info/requires.txt
Products.BooleanIndex.egg-info/top_level.txt
Products/BooleanIndex/BooleanIndex.py
Products/BooleanIndex/__init__.py
Products/BooleanIndex/tests.py
Products/BooleanIndex/dtml/addBooleanIndex.dtml
Products/BooleanIndex/dtml/browseIndex.dtml
Products/BooleanIndex/dtml/manageBooleanIndex.dtml
Products/BooleanIndex/www/index.gif
docs/LICENSE.GPL
docs/LICENSE.txt