Metadata-Version: 1.0
Name: Products.BooleanIndex
Version: 1.0.1
Summary: UNKNOWN
Home-page: http://pypi.python.org/pypi/Products.BooleanIndex
Author: Jarn AS
Author-email: info@jarn.com
License: GPL
Platform: UNKNOWN
Classifier: Framework :: Plone
Classifier: Programming Language :: Python
